autoXRD/__init__.py
autoXRD/cnn/__init__.py
autoXRD/dara/.DS_Store
autoXRD/dara/__init__.py
autoXRD/dara/data/.DS_Store
autoXRD/dara/data/.gitignore
autoXRD/dara/data/__init__.py
autoXRD/dara/data/possible_species.txt
autoXRD/dara/data/BGMN-Templates/Devices/ALBA-BM16.geq
autoXRD/dara/data/BGMN-Templates/Devices/ALBA-BM16.ger
autoXRD/dara/data/BGMN-Templates/Devices/ALBA-BM16.sav
autoXRD/dara/data/BGMN-Templates/Devices/ALBA-BM16.tpl
autoXRD/dara/data/BGMN-Templates/Devices/Aeris-fds-Pixcel1d-Medipix3.geq
autoXRD/dara/data/BGMN-Templates/Devices/Aeris-fds-Pixcel1d-Medipix3.ger
autoXRD/dara/data/BGMN-Templates/Devices/Aeris-fds-Pixcel1d-Medipix3.sav
autoXRD/dara/data/BGMN-Templates/Devices/Aeris-fds-Pixcel1d-Medipix3.tpl
autoXRD/dara/data/BGMN-Templates/Devices/D8_6Div_4SS.geq
autoXRD/dara/data/BGMN-Templates/Devices/D8_6Div_4SS.ger
autoXRD/dara/data/BGMN-Templates/Devices/D8_6Div_4SS.sav
autoXRD/dara/data/BGMN-Templates/Devices/D8_6Div_4SS.tpl
autoXRD/dara/data/BGMN-Templates/Devices/D8_Oslo_Geo.geq
autoXRD/dara/data/BGMN-Templates/Devices/D8_Oslo_Geo.ger
autoXRD/dara/data/BGMN-Templates/Devices/D8_Oslo_Geo.sav
autoXRD/dara/data/BGMN-Templates/Devices/D8_Oslo_Geo.tpl
autoXRD/dara/data/BGMN-Templates/Devices/FUB-PhysGeog-Empyrean-fds0125.SAV
autoXRD/dara/data/BGMN-Templates/Devices/FUB-PhysGeog-Empyrean-fds0125.geq
autoXRD/dara/data/BGMN-Templates/Devices/FUB-PhysGeog-Empyrean-fds0125.ger
autoXRD/dara/data/BGMN-Templates/Devices/FUB-PhysGeog-Empyrean-fds0125.tpl
autoXRD/dara/data/BGMN-Templates/Devices/FUB-PhysGeog-Rigaku-Miniflex.SAV
autoXRD/dara/data/BGMN-Templates/Devices/FUB-PhysGeog-Rigaku-Miniflex.geq
autoXRD/dara/data/BGMN-Templates/Devices/FUB-PhysGeog-Rigaku-Miniflex.ger
autoXRD/dara/data/BGMN-Templates/Devices/FUB-PhysGeog-Rigaku-Miniflex.tpl
autoXRD/dara/data/BGMN-Templates/Devices/GC-Synchrotron.geq
autoXRD/dara/data/BGMN-Templates/Devices/GC-Synchrotron.ger
autoXRD/dara/data/BGMN-Templates/Devices/GC-Synchrotron.sav
autoxrd-0.0.7.dist-info/licenses/LICENSE
autoxrd-0.0.7.dist-info/METADATA
autoxrd-0.0.7.dist-info/WHEEL
autoxrd-0.0.7.dist-info/top_level.txt
autoxrd-0.0.7.dist-info/RECORD
