Metadata-Version: 2.4
Name: autoXRD
Version: 0.0.7
Summary: A package for automated XRD analysis
Home-page: https://github.com/njszym/XRD-AutoAnalyzer
Author: Nathan J. Szymanski
Author-email: "Nathan J. Szymanski" <nathan_szymanski@berkeley.edu>
License: MIT
Project-URL: Homepage, https://github.com/njszym/XRD-AutoAnalyzer
Classifier: Programming Language :: Python :: 3
Classifier: License :: OSI Approved :: MIT License
Classifier: Operating System :: OS Independent
Requires-Python: >=3.7
License-File: LICENSE
Requires-Dist: numpy
Requires-Dist: pymatgen
Requires-Dist: scipy
Requires-Dist: scikit-image
Requires-Dist: tensorflow>=2.16
Requires-Dist: pyxtal
Requires-Dist: pyts
Requires-Dist: tqdm
Requires-Dist: asteval
Requires-Dist: numexpr>=2.8.3
Dynamic: author
Dynamic: home-page
Dynamic: license-file
Dynamic: requires-python
